sky_api_client/__init__.py
sky_api_client/client.py
sky_api_client/common/__init__.py
sky_api_client/common/tasks/__init__.py
sky_api_client/common/tasks/asyncio.py
sky_api_client/entity/__init__.py
sky_api_client/entity/action.py
sky_api_client/entity/action_custom_field.py
sky_api_client/entity/action_status.py
sky_api_client/entity/address.py
sky_api_client/entity/base.py
sky_api_client/entity/code_table.py
sky_api_client/entity/constituent.py
sky_api_client/entity/constituent_address.py
sky_api_client/entity/constituent_code.py
sky_api_client/entity/constituent_custom_field.py
sky_api_client/entity/constituent_education.py
sky_api_client/entity/constituent_email_address.py
sky_api_client/entity/constituent_online_presence.py
sky_api_client/entity/constituent_phone.py
sky_api_client/entity/constituent_relationship.py
sky_api_client/entity/constituent_solicit_code.py
sky_api_client/entity/custom_field.py
sky_api_client/entity/custom_field_categories.py
sky_api_client/entity/education.py
sky_api_client/entity/email_addresses.py
sky_api_client/entity/event.py
sky_api_client/entity/event_fee.py
sky_api_client/entity/event_participant.py
sky_api_client/entity/event_participant_donation.py
sky_api_client/entity/event_participant_fee.py
sky_api_client/entity/event_participant_fee_payment.py
sky_api_client/entity/event_participant_levels.py
sky_api_client/entity/event_participation_levels.py
sky_api_client/entity/fundraising_appeal.py
sky_api_client/entity/fundraising_campaign.py
sky_api_client/entity/fundraising_fund.py
sky_api_client/entity/fundraising_package.py
sky_api_client/entity/gender.py
sky_api_client/entity/gift.py
sky_api_client/entity/gift_aid.py
sky_api_client/entity/gift_batch.py
sky_api_client/entity/gift_batch_gift.py
sky_api_client/entity/gift_batch_gift_v2.py
sky_api_client/entity/gift_custom_field_values.py
sky_api_client/entity/gift_custom_fields.py
sky_api_client/entity/gift_subtype.py
sky_api_client/entity/list.py
sky_api_client-3.3.8.dist-info/LICENSE
sky_api_client-3.3.8.dist-info/METADATA
sky_api_client-3.3.8.dist-info/WHEEL
sky_api_client-3.3.8.dist-info/top_level.txt
sky_api_client-3.3.8.dist-info/RECORD
