Metadata-Version: 2.1
Name: sky-api-client
Version: 3.3.8
Summary: Python client for RENXT APIs
Home-page: https://bitbucket.org/kalyanvarma/skyapi
Author: Rajeev K L
Author-email: rajeev@almabase.com
License: UNKNOWN
Platform: UNKNOWN
Classifier: Programming Language :: Python :: 3
Classifier: License :: OSI Approved :: MIT License
Classifier: Operating System :: OS Independent
Requires-Python: >=3.5
